CompartirIgualdad/__init__.py
CompartirIgualdad/__main__.py
CompartirIgualdad/static/css/bootstrap.min.css
CompartirIgualdad/static/css/font.scss
CompartirIgualdad/static/css/style.min.css
CompartirIgualdad/static/css/style.scss
CompartirIgualdad/static/fonts/poppins/poppins-v5-latin-300.eot
CompartirIgualdad/static/fonts/poppins/poppins-v5-latin-300.svg
CompartirIgualdad/static/fonts/poppins/poppins-v5-latin-300.ttf
CompartirIgualdad/static/fonts/poppins/poppins-v5-latin-300.woff
CompartirIgualdad/static/fonts/poppins/poppins-v5-latin-300.woff2
CompartirIgualdad/static/fonts/poppins/poppins-v5-latin-600.eot
CompartirIgualdad/static/fonts/poppins/poppins-v5-latin-600.svg
CompartirIgualdad/static/fonts/poppins/poppins-v5-latin-600.ttf
CompartirIgualdad/static/fonts/poppins/poppins-v5-latin-600.woff
CompartirIgualdad/static/fonts/poppins/poppins-v5-latin-600.woff2
CompartirIgualdad/static/images/compartirigualdad.png
CompartirIgualdad/static/images/favicon.ico
CompartirIgualdad/static/js/jquery-3.4.1.min.js
CompartirIgualdad/static/js/main.js
CompartirIgualdad/static/vendor/datatable/datatables.min.css
CompartirIgualdad/static/vendor/datatable/datatables.min.js
CompartirIgualdad/static/vendor/datatable/file-size.js
CompartirIgualdad/static/vendor/datatable/DataTables-1.10.18/images/sort_asc.png
CompartirIgualdad/static/vendor/datatable/DataTables-1.10.18/images/sort_asc_disabled.png
CompartirIgualdad/static/vendor/datatable/DataTables-1.10.18/images/sort_both.png
CompartirIgualdad/static/vendor/datatable/DataTables-1.10.18/images/sort_desc.png
CompartirIgualdad/static/vendor/datatable/DataTables-1.10.18/images/sort_desc_disabled.png
CompartirIgualdad/static/vendor/fontawesome-5.1/LICENSE.txt
CompartirIgualdad/static/vendor/fontawesome-5.1/css/all.min.css
CompartirIgualdad/static/vendor/fontawesome-5.1/webfonts/fa-brands-400.eot
CompartirIgualdad/static/vendor/fontawesome-5.1/webfonts/fa-brands-400.svg
CompartirIgualdad-1.5.dist-info/METADATA
CompartirIgualdad-1.5.dist-info/WHEEL
CompartirIgualdad-1.5.dist-info/entry_points.txt
CompartirIgualdad-1.5.dist-info/top_level.txt
CompartirIgualdad-1.5.dist-info/RECORD
